foamstream/__init__.py
foamstream/logger.py
foamstream/streamer.py
foamstream/euxfel/__init__.py
foamstream/euxfel/app.py
foamstream/euxfel/file_server.py
foamstream/euxfel/gui.py
foamstream/euxfel/icons/repeat.png
foamstream/euxfel/icons/start.png
foamstream/euxfel/icons/stop.png
foamstream/tests/__init__.py
foamstream/tests/conftest.py
foamstream/tests/test_streamer.py
foamstream/tomo/__init__.py
foamstream/tomo/app.py
foamstream/tomo/tests/__init__.py
foamstream/tomo/tests/test_tomo_app.py
foamstream/tomo/tests/tomo_consumer.py
foamstream/writer/__init__.py
foamstream/writer/writer.py
foamstream-0.2.3.dist-info/LICENSE
foamstream-0.2.3.dist-info/METADATA
foamstream-0.2.3.dist-info/WHEEL
foamstream-0.2.3.dist-info/entry_points.txt
foamstream-0.2.3.dist-info/top_level.txt
foamstream-0.2.3.dist-info/RECORD
