Metadata-Version: 2.1
Name: foamstream
Version: 0.2.3
Author-email: Jun Zhu <zhujun981661@gmail.com>
License: BSD 3-Clause License
Project-URL: repository, https://github.com/zhujun98/foamstream
Classifier: Development Status :: 4 - Beta
Classifier: Intended Audience :: Developers
Classifier: License :: OSI Approved :: BSD License
Classifier: Operating System :: OS Independent
Classifier: Programming Language :: Python :: 3.9
Classifier: Programming Language :: Python :: 3.10
Classifier: Topic :: Scientific/Engineering :: Information Analysis
Requires-Python: >=3.9
License-File: LICENSE
Requires-Dist: h5py >=3.7.0
Requires-Dist: numpy
Requires-Dist: foamclient >=0.2.0
Provides-Extra: euxfel
Requires-Dist: foamgraph ; extra == 'euxfel'
Requires-Dist: extra-data ; extra == 'euxfel'
Requires-Dist: karabo-bridge ; extra == 'euxfel'
Provides-Extra: test
Requires-Dist: pytest ; extra == 'test'
Requires-Dist: pytest-cov ; extra == 'test'
